HISTORY.rst
LICENSE.rst
MANIFEST.in
README.rst
setup.py
src/relstorage_packer/__init__.py
src/relstorage_packer/refcount.py
src/relstorage_packer/utils.py
src/relstorage_packer.egg-info/PKG-INFO
src/relstorage_packer.egg-info/SOURCES.txt
src/relstorage_packer.egg-info/dependency_links.txt
src/relstorage_packer.egg-info/entry_points.txt
src/relstorage_packer.egg-info/requires.txt
src/relstorage_packer.egg-info/top_level.txt
src/relstorage_packer.egg-info/zip-safe