Metadata-Version: 1.1
Name: relstorage-packer
Version: 1.0
Summary: Packs a History Free PostgreSQL RelStorage for ZODB.
Home-page: http://pypi.python.org/pypi/relstorage_packer
Author: BlueDynamics Alliance
Author-email: dev@bluedynamics.com
License: Simplified BSD
Keywords: postgresql zodb pack zope
Platform: UNKNOWN
Classifier: Operating System :: OS Independent
Classifier: Programming Language :: Python
Classifier: Topic :: Software Development
Classifier: License :: OSI Approved :: BSD License
